{"1":{"id":1,"level":1,"title":"two-sum","language":["javascript"],"generated":true},"2":{"id":2,"level":2,"title":"add-two-numbers","language":["javascript"],"generated":true},"3":{"id":3,"level":2,"title":"longest-substring-without-repeating-characters","language":["javascript"],"generated":true},"4":{"id":4,"level":3,"title":"median-of-two-sorted-arrays","language":["javascript"],"generated":true},"7":{"id":7,"level":1,"title":"reverse-integer","language":["javascript"],"generated":true},"8":{"id":8,"level":2,"title":"string-to-integer-atoi","language":["javascript"],"generated":true},"26":{"id":26,"level":1,"title":"remove-duplicates-from-sorted-array","language":["javascript"],"generated":true},"141":{"id":141,"level":1,"title":"linked-list-cycle","language":["javascript"],"generated":true},"142":{"id":142,"level":2,"title":"linked-list-cycle-ii","language":["javascript"],"generated":true},"380":{"id":380,"level":2,"title":"insert-delete-getrandom-o1","language":["javascript"],"generated":true},"lastUpdatedTime":"2017-12-16","total":660,"solved":10,"locked":120}